mimerpy/__init__.py
mimerpy/__main__.py
mimerpy/_version.py
mimerpy/connectionPy.py
mimerpy/cursorPy.py
mimerpy/mimPyErrorCodes.py
mimerpy/mimPyExceptionHandler.py
mimerpy/mimPyExceptions.py
mimerpy/mimerapi.py
mimerpy/pool.py
mimerpy/utils.py
mimerpy-1.3.6.dist-info/LICENSE.txt
mimerpy-1.3.6.dist-info/METADATA
mimerpy-1.3.6.dist-info/WHEEL
mimerpy-1.3.6.dist-info/top_level.txt
mimerpy-1.3.6.dist-info/RECORD
