Metadata-Version: 2.2
Name: mimerpy
Version: 1.3.6
Summary: Python database interface for Mimer SQL
Author-email: Erik Gunne <mimerpy@mimer.com>, Magdalena Boström <mimerpy@mimer.com>, Mimer Information Technology AB <mimerpy@mimer.com>
Maintainer-email: Mimer Information Technology AB <mimerpy@mimer.com>
License: MIT
Project-URL: Homepage, https://developer.mimer.com/mimerpy
Keywords: Mimer,MimerSQL,Database,SQL,PEP249
Classifier: Development Status :: 5 - Production/Stable
Classifier: Intended Audience :: Developers
Classifier: Topic :: Software Development :: Build Tools
Classifier: Programming Language :: Python :: 3.6
Classifier: Programming Language :: Python :: 3.7
Classifier: Programming Language :: Python :: 3.8
Classifier: Programming Language :: Python :: 3.9
Classifier: Programming Language :: Python :: 3.10
Classifier: Programming Language :: Python :: 3.11
Classifier: Programming Language :: Python :: 3.12
Classifier: Programming Language :: Python :: 3.13
Requires-Python: >=3.6
License-File: LICENSE.txt
Requires-Dist: python-dateutil>=2.8.2; python_version < "3.7"
